cryptoluggage/__init__.py
cryptoluggage/__main__.py
cryptoluggage/luggage.py
cryptoluggage/model.py
cryptoluggage-3.1.4.dist-info/licenses/LICENSE
cryptoluggage-3.1.4.dist-info/METADATA
cryptoluggage-3.1.4.dist-info/WHEEL
cryptoluggage-3.1.4.dist-info/entry_points.txt
cryptoluggage-3.1.4.dist-info/top_level.txt
cryptoluggage-3.1.4.dist-info/RECORD
