Metadata-Version: 2.4
Name: cryptoluggage
Version: 3.1.4
Summary: Cryptoluggage allows to keep encrypted secrets (e.g., passwords) and files
Author-email: Miguel Hernández Cabronero <miguel.hernandez@uab.cat>
License-Expression: MIT
Project-URL: Homepage, https://github.com/miguelinux314/cryptoluggage
Classifier: Programming Language :: Python :: 3
Classifier: Operating System :: OS Independent
Requires-Python: >=3.8
License-File: LICENSE
Requires-Dist: cryptography
Requires-Dist: sortedcontainers
Requires-Dist: prompt_toolkit
Requires-Dist: qrcode
Requires-Dist: portalocker
Dynamic: license-file
